lols/__init__.py
lols/__main__.py
lols/config.py
lols/exceptions.py
lols/path_creator.py
lols/settings.py
lols/utils.py
lols/version.py
lols/http/__init__.py
lols/http/client.py
lols/http/downloader.py
lols/http/headers.py
lols/http/m3u8_downloader.py
lols/http/models.py
lols/http/types.py
lols/scrapers/__init__.py
lols/scrapers/_scraper_base.py
lols/scrapers/_scraper_template.py
lols/scrapers/all_scrapers.py
lols/scrapers/anonfiles.py
lols/scrapers/bunkr.py
lols/scrapers/cyberdrop.py
lols/scrapers/erome.py
lols/scrapers/forum_nudostar.py
lols/scrapers/forum_nudostar_auth.py
lols/scrapers/forum_socialmediagirls.py
lols/scrapers/forum_socialmediagirls_auth.py
lols/scrapers/forum_thotsbay.py
lols/scrapers/forum_thotsbay_auth.py
lols/scrapers/gofile.py
lols/scrapers/gofile_auth.py
lols/scrapers/hexupload.py
lols/scrapers/highload.py
lols/scrapers/ibb.py
lols/scrapers/imagebam.py
lols/scrapers/imagehaha.py
lols/scrapers/imagetwist.py
lols/scrapers/imgbox.py
lols/scrapers/jpgchurch.py
lols/scrapers/leakedmodelsforum.py
lols/scrapers/leakedmodelsforum_auth.py
lols/scrapers/lovefap.py
lols/scrapers/mega.py
lols/scrapers/pixeldrain.py
lols/scrapers/pixhost.py
lols/scrapers/pixl.py
lols/scrapers/planetsuzy.py
lols/scrapers/saint.py
lols/scrapers/sendvid.py
lols/scrapers/simpcity.py
lols/scrapers/simpcity_auth.py
lols/scrapers/skygallery.py
lols/scrapers/streamlare.py
lols/scrapers/streamtape.py
lols/scrapers/voe.py
lols/scrapers/xvideos.py
lol_site_scraper-2.0.1.dist-info/LICENSE
lol_site_scraper-2.0.1.dist-info/METADATA
lol_site_scraper-2.0.1.dist-info/WHEEL
lol_site_scraper-2.0.1.dist-info/entry_points.txt
lol_site_scraper-2.0.1.dist-info/top_level.txt
lol_site_scraper-2.0.1.dist-info/RECORD
