Metadata-Version: 2.1
Name: lol-site-scraper
Version: 2.0.1
Summary: Bulk hosting sites scraper/downloader
Home-page: https://github.com/vladimirpolak/lols
Author: Vladimír Polák
Author-email: vladimirpolak2@gmail.com
License: MIT
Platform: UNKNOWN
License-File: LICENSE
Requires-Dist: requests
Requires-Dist: retry
Requires-Dist: w3lib
